pr_review_cli/__init__.py
pr_review_cli/cli.py
pr_review_cli-0.1.0.dist-info/METADATA
pr_review_cli-0.1.0.dist-info/WHEEL
pr_review_cli-0.1.0.dist-info/entry_points.txt
pr_review_cli-0.1.0.dist-info/top_level.txt
pr_review_cli-0.1.0.dist-info/RECORD
