Metadata-Version: 2.4
Name: pr-review-cli
Version: 0.1.0
Summary: A CLI dashboard for managing PR review history and rechecks
Author-email: Ahmed Sulaimon <sulaimonahmed10@gmail.com>
License: MIT
Requires-Python: >=3.8
Requires-Dist: httpx>=0.25
